diff_llm/__init__.py
diff_llm/create_dataset.py
diff_llm/data_loader.py
diff_llm/fine_tune.py
diff_llm-0.0.0a0.data/data/LICENSE
diff_llm-0.0.0a0.dist-info/LICENSE
diff_llm-0.0.0a0.dist-info/METADATA
diff_llm-0.0.0a0.dist-info/WHEEL
diff_llm-0.0.0a0.dist-info/top_level.txt
diff_llm-0.0.0a0.dist-info/RECORD
